Statech/__init__.py
Statech/spssbase.py
Statech/correlation_model/__init__.py
Statech/correlation_model/canonical_correlation_analysis.py
Statech/factor_model/__init__.py
Statech/factor_model/validation_factor.py
Statech/generation_alogrithm_model/GA.py
Statech/generation_alogrithm_model/__init__.py
Statech/generation_alogrithm_model/_base.py
Statech/generation_alogrithm_model/tool.py
Statech/generation_alogrithm_model/operators/__init__.py
Statech/generation_alogrithm_model/operators/crossover.py
Statech/generation_alogrithm_model/operators/mutation.py
Statech/generation_alogrithm_model/operators/ranking.py
Statech/generation_alogrithm_model/operators/selection.py
Statech/linear_model/__init__.py
Statech/linear_model/_base.py
Statech/linear_model/linear_model.py
Statech/metrics/__init__.py
Statech/metrics/_regression.py
Statech/pojo/__init__.py
Statech/pojo/errors.py
statis_learn-0.0.4.dist-info/LICENSE
statis_learn-0.0.4.dist-info/METADATA
statis_learn-0.0.4.dist-info/WHEEL
statis_learn-0.0.4.dist-info/top_level.txt
statis_learn-0.0.4.dist-info/RECORD
